{
  "project_info": {
    "project_number": "383280075229",
    "project_id": "payit-hbz",
    "storage_bucket": "payit-hbz.firebasestorage.app"
  },
  "client": [
    {
      "client_info": {
        "mobilesdk_app_id": "1:383280075229:android:b45764cd1210f7e453a634",
        "android_client_info": {
          "package_name": "com.example.pay_it"
        }
      },
      "oauth_client": [],
      "api_key": [
        {
          "current_key": "AIzaSyDYLjt0ZQ4ahtT-JzKOJGAG4brR7VjPJGw"
        }
      ],
      "services": {
        "appinvite_service": {
          "other_platform_oauth_client": []
        }
      }
    }
  ],
  "configuration_version": "1"
}